osm_mcp_server/__init__.py
osm_mcp_server/server.py
osm_mcp_server-0.1.1.dist-info/METADATA
osm_mcp_server-0.1.1.dist-info/WHEEL
osm_mcp_server-0.1.1.dist-info/entry_points.txt
osm_mcp_server-0.1.1.dist-info/licenses/LICENSE
osm_mcp_server-0.1.1.dist-info/RECORD
