Metadata-Version: 2.4
Name: osm-mcp-server
Version: 0.1.1
Summary: An OpenStreetMap MCP server
Author-email: Jagan Shanmugam <jaganshanmugam@outlook.com>
License-File: LICENSE
Requires-Python: >=3.13
Requires-Dist: aiohttp>=3.11.13
Requires-Dist: mcp[cli]>=1.3.0
